quarchpy/LICENSE.rst
quarchpy/QuarchPy Function Listing.xlsx
quarchpy/README.txt
quarchpy/__init__.py
quarchpy/_version.py
quarchpy/connection.py
quarchpy/run.py
quarchpy/config_files/__init__.py
quarchpy/config_files/quarch_config_parser.py
quarchpy/config_files/Cable_Modules/QTL1253-01 - Mini SAS Module Config v3.5 c1.3.qfg
quarchpy/config_files/Cable_Modules/QTL1253-01 - Mini SAS Module Config v4.000 c1.3.qfg
quarchpy/config_files/Cable_Modules/QTL1253-02 - Mini SAS Module Config v3.5 c1.3.qfg
quarchpy/config_files/Cable_Modules/QTL1253-02 - Mini SAS Module Config v4.000 c1.3.qfg
quarchpy/config_files/Cable_Modules/QTL1253-xx - Mini SAS Module Config v4.003 c1.6.qfg
quarchpy/config_files/Cable_Modules/QTL1271-xx - Ethernet Module Config v3.5 c1.2.qfg
quarchpy/config_files/Cable_Modules/QTL1271-xx - Ethernet Module Config v4.000 c1.2.qfg
quarchpy/config_files/Cable_Modules/QTL1271-xx - Ethernet Module Config v4.100 c1.3.qfg
quarchpy/config_files/Cable_Modules/QTL1292-xx - SFP+ Cable Pull Module Config v4.000 c1.1.qfg
quarchpy/config_files/Cable_Modules/QTL1309-04 - USB 3.0 Module Config v4.003 c1.2.qfg
quarchpy/config_files/Cable_Modules/QTL1309-xx - USB 3.0 Module Config v3.5 c1.1.qfg
quarchpy/config_files/Cable_Modules/QTL1309-xx - USB 3.0 Module Config v4.000 c1.1.qfg
quarchpy/config_files/Cable_Modules/QTL1366-xx - QSFP Cable Pull Module Config v4.000 c1.1.qfg
quarchpy/config_files/Cable_Modules/QTL1383-xx - eSATAp Module Config v4.000 c1.3.qfg
quarchpy/config_files/Cable_Modules/QTL1521-02 - Mini SAS HD Module Config v4.000 c1.1.qfg
quarchpy/config_files/Cable_Modules/QTL1521-03 - Mini SAS HD Module Config v4.000 c1.1.qfg
quarchpy/config_files/Cable_Modules/QTL1521-05 - Mini SAS HD Module Config v4.005 c1.1.qfg
quarchpy/config_files/Cable_Modules/QTL1521-05 - Mini SAS HD Module Config v4.007 c1.2.qfg
quarchpy/config_files/Cable_Modules/QTL1521-xx - Mini SAS HD Module Config v4.003 c1.5.qfg
quarchpy_test-2.1.0.dist-info/METADATA
quarchpy_test-2.1.0.dist-info/WHEEL
quarchpy_test-2.1.0.dist-info/top_level.txt
quarchpy_test-2.1.0.dist-info/RECORD
