Metadata-Version: 2.1
Name: quarchpy-test
Version: 2.1.0
Summary: This packpage offers Python support for Quarch Technology modules.
Home-page: UNKNOWN
Author: Quarch Technology ltd
Author-email: support@quarch.com
License: Quarch Technology ltd
Keywords: quarch quarchpy torridon
Platform: UNKNOWN
Classifier: Intended Audience :: Information Technology
Classifier: Intended Audience :: Developers
Classifier: Natural Language :: English
Classifier: Operating System :: MacOS
Classifier: Operating System :: Microsoft :: Windows
Classifier: Operating System :: POSIX
Classifier: Programming Language :: Python
Classifier: Topic :: Scientific/Engineering :: Information Analysis
Classifier: Topic :: System
Classifier: Topic :: System :: Power (UPS)
